minimum_versions/__init__.py
minimum_versions/__main__.py
minimum_versions/formatting.py
minimum_versions/main.py
minimum_versions/policy.py
minimum_versions/release.py
minimum_versions/environments/__init__.py
minimum_versions/environments/conda.py
minimum_versions/environments/pixi.py
minimum_versions/environments/spec.py
minimum_versions/tests/test_environments.py
minimum_versions/tests/test_policy.py
minimum_versions/tests/test_release.py
minimum_versions/tests/test_spec.py
xarray_minimum_dependency_policy-2.0.0.dist-info/METADATA
xarray_minimum_dependency_policy-2.0.0.dist-info/WHEEL
xarray_minimum_dependency_policy-2.0.0.dist-info/entry_points.txt
xarray_minimum_dependency_policy-2.0.0.dist-info/licenses/LICENSE
xarray_minimum_dependency_policy-2.0.0.dist-info/RECORD
