Metadata-Version: 2.4
Name: xarray-minimum-dependency-policy
Version: 2.0.0
Summary: Validate minimum dependency environments according to xarray's policy scheme
Project-URL: Repository, https://github.com/xarray-contrib/minimum-dependency-versions
Author: Justus Magin
License-Expression: Apache-2.0
License-File: LICENSE
Requires-Python: >=3.11
Requires-Dist: cytoolz>=1.1.0
Requires-Dist: jsonschema>=4.25.0
Requires-Dist: py-rattler>=0.20.0
Requires-Dist: python-dateutil>=2.9.0
Requires-Dist: pyyaml>=6.0.0
Requires-Dist: rich-click>=1.9.0
Requires-Dist: rich>=14.2.0
